{
  "canisters": {
    "nalanet": {
      "main": "src/nalanet/main.mo",
      "type": "motoko"
    },
    "nalanet_assets": {
      "dependencies": [
        "nalanet"
      ],
      "frontend": {
        "entrypoint": "src/nalanet_assets/public/index.js"
      },
      "source": [
        "src/nalanet_assets/assets",
        "dist/nalanet_assets/"
      ],
      "type": "assets"
    }
  },
  "defaults": {
    "build": {
      "packtool": ""
    }
  },
  "dfx": "0.6.26",
  "networks": {
    "local": {
      "bind": "127.0.0.1:8000",
      "type": "ephemeral"
    }
  },
  "version": 1
}